gcodeutils-1.3.2.dist-info/WHEEL
gcodeutils-1.3.2.dist-info/top_level.txt
gcodeutils-1.3.2.dist-info/RECORD
gcodeutils-1.3.2.dist-info/metadata.json
gcodeutils-1.3.2.dist-info/entry_points.txt
gcodeutils-1.3.2.dist-info/METADATA
gcodeutils-1.3.2.dist-info/DESCRIPTION.rst
gcodeutils/gcode_stretch.py
gcodeutils/gcoder.py
gcodeutils/gcode_optimize_arcs.py
gcodeutils/__init__.py
gcodeutils/gcode_tempcal.py
gcodeutils/gcode_mod.py
gcodeutils/filter/filter.py
gcodeutils/filter/arc_optimizer.py
gcodeutils/filter/translate.py
gcodeutils/filter/relative_extrusion.py
gcodeutils/filter/__init__.py
gcodeutils/tests/test_modification.py
gcodeutils/tests/test_stretch.py
gcodeutils/tests/test_equality.py
gcodeutils/tests/test_arc_optimization.py
gcodeutils/tests/__init__.py
gcodeutils/tests/test_iterator.py
gcodeutils/stretch/vector3.py
gcodeutils/stretch/stretch.py
gcodeutils/stretch/__init__.py
gcodeutils-1.3.2.data/data/cura_plugins/stretch_plugin.py
gcodeutils-1.3.2.data/data/cura_plugins/tempcal_plugin.py
