Metadata-Version: 2.0
Name: gcodeutils
Version: 1.3.2
Summary: Reprap oriented gcode utilities
Home-page: https://github.com/zeograd/gcodeutils
Author: Olivier Jolly
Author-email: olivier@pcedev.com
License: GPLv2+
Keywords: reprap,gcode,calibration,stretch,arc compensation,arc optimization,arc conversion
Platform: UNKNOWN
Classifier: Development Status :: 5 - Production/Stable
Classifier: Environment :: Console
Classifier: Intended Audience :: Science/Research
Classifier: Topic :: Multimedia :: Graphics :: 3D Modeling
Classifier: License :: OSI Approved :: GNU General Public License v2 or later (GPLv2+)
Classifier: Programming Language :: Python :: 2
Classifier: Programming Language :: Python :: 2.7
Classifier: Programming Language :: Python :: 3
Classifier: Programming Language :: Python :: 3.2
Classifier: Programming Language :: Python :: 3.3
Classifier: Programming Language :: Python :: 3.4
Classifier: Programming Language :: Python :: 3.5
Provides-Extra: dev
Requires-Dist: check-manifest; extra == 'dev'
Requires-Dist: pylint; extra == 'dev'
Provides-Extra: test
Requires-Dist: nose; extra == 'test'
